hdytools/__init__.py
hdytools/basic.py
hdytools/ml_lib.py
hdytools-0.4.dist-info/METADATA
hdytools-0.4.dist-info/WHEEL
hdytools-0.4.dist-info/top_level.txt
hdytools-0.4.dist-info/RECORD
