Metadata-Version: 2.1
Name: hdytools
Version: 0.4
Summary: Machine Learning Libraries
Home-page: http://github.com/horngderyang/hdytools
Author: horngderyang
Author-email: horngderyang@gmail.com
License: UNKNOWN
Platform: UNKNOWN
Classifier: Programming Language :: Python :: 3
Classifier: License :: OSI Approved :: MIT License
Classifier: Operating System :: OS Independent
Requires-Python: >=3.6
